rgpvApi/__init__.py
rgpvApi/info_api.py
rgpvApi/result_api.py
rgpvApi-1.0.2.dist-info/LICENSE.txt
rgpvApi-1.0.2.dist-info/METADATA
rgpvApi-1.0.2.dist-info/WHEEL
rgpvApi-1.0.2.dist-info/top_level.txt
rgpvApi-1.0.2.dist-info/RECORD
